viral_rna_simulation/__init__.py
viral_rna_simulation/cell.py
viral_rna_simulation/cells.py
viral_rna_simulation/cli.py
viral_rna_simulation/genome.py
viral_rna_simulation/rna.py
viral_rna_simulation/simulate.py
viral_rna_simulation/site.py
viral_rna_simulation/utils.py
viral_rna_simulation-0.1.0.dist-info/METADATA
viral_rna_simulation-0.1.0.dist-info/WHEEL
viral_rna_simulation-0.1.0.dist-info/entry_points.txt
viral_rna_simulation-0.1.0.dist-info/RECORD
