Metadata-Version: 2.4
Name: viral-rna-simulation
Version: 0.1.0
Summary: A simulation of replication of viral RNA
Author-email: terrycojones <terence.jones@charite.de>
Requires-Python: >=3.13
